hello/__init__.py
hello/helloworld.py
helloworldtestpackage-0.0.1.dist-info/LICENSE
helloworldtestpackage-0.0.1.dist-info/METADATA
helloworldtestpackage-0.0.1.dist-info/WHEEL
helloworldtestpackage-0.0.1.dist-info/top_level.txt
helloworldtestpackage-0.0.1.dist-info/RECORD
