Metadata-Version: 2.1
Name: helloworldtestpackage
Version: 0.0.1
Summary: Test hello package description
Home-page: UNKNOWN
Author: NeuralNine (Florian Dedov)
Author-email: <mail@neuralnine.com>
License: UNKNOWN
Keywords: hello,hi,hello world
Platform: UNKNOWN
Classifier: Development Status :: 1 - Planning
Classifier: Intended Audience :: Developers
Classifier: Programming Language :: Python :: 3
Classifier: Operating System :: Unix
Classifier: Operating System :: MacOS :: MacOS X
Classifier: Operating System :: Microsoft :: Windows
